{
  "db_name": "PostgreSQL",
  "query": "\n            SELECT id, task_id, provider, cid, request_id, status, requestor\n            FROM pin_requests\n            WHERE status IN ('queued', 'pinning')\n            ORDER BY id\n            ",
  "describe": {
    "columns": [
      {
        "ordinal": 0,
        "name": "id",
        "type_info": "Int8"
      },
      {
        "ordinal": 1,
        "name": "task_id",
        "type_info": "Varchar"
      },
      {
        "ordinal": 2,
        "name": "provider",
        "type_info": "Varchar"
      },
      {
        "ordinal": 3,
        "name": "cid",
        "type_info": "Varchar"
      },
      {
        "ordinal": 4,
        "name": "request_id",
        "type_info": "Varchar"
      },
      {
        "ordinal": 5,
        "name": "status",
        "type_info": "Varchar"
      },
      {
        "ordinal": 6,
        "name": "requestor",
        "type_info": "Varchar"
      }
    ],
    "parameters": {
      "Left": []
    },
    "nullable": [
      false,
      false,
      false,
      false,
      false,
      false,
      false
    ]
  },
  "hash": "947892aaa4ddc23fa2e7a0bf065c2bf3ea374236da4010fe43fac814b18c6058"
}
